Fake_job.py
jobs.txt
User_Data.txt
itarj_app-1.0.1.dist-info/entry_points.txt
itarj_app-1.0.1.dist-info/WHEEL
itarj_app-1.0.1.dist-info/METADATA
itarj_app-1.0.1.dist-info/RECORD
