Metadata-Version: 2.1
Name: itarj-app
Version: 1.0.1
Summary: ITARJ CONSOLE: A console app that allows users to register fake job alerts and allows others to view those posts by searching for keywords.
Author: Emmanuel Chijioke aka DREL
Requires-Python: >3.0
Classifier: Programming Language :: Python :: 3
Classifier: Programming Language :: Python :: 3.4
Classifier: Programming Language :: Python :: 3.5
Classifier: Programming Language :: Python :: 3.6
Classifier: Programming Language :: Python :: 3.7
Classifier: Programming Language :: Python :: 3.8
